gptdjmme/__init__.py
gptdjmme/ai.py
gptdjmme/db.py
gptdjmme/main.py
gptdjmme-0.0.9.dist-info/LICENSE
gptdjmme-0.0.9.dist-info/METADATA
gptdjmme-0.0.9.dist-info/WHEEL
gptdjmme-0.0.9.dist-info/top_level.txt
gptdjmme-0.0.9.dist-info/RECORD
