Metadata-Version: 2.1
Name: gptdjmme
Version: 0.0.9
Summary: A python package to clone yourself with GPT
Author: Daniel J. McDonald
Author-email: <daniel@danielmcdonald.dev>
Keywords: python,gpt,openai,ai,chatbot,clone,me
Classifier: Development Status :: 1 - Planning
Classifier: Intended Audience :: Developers
Classifier: Programming Language :: Python :: 3
Classifier: Operating System :: OS Independent
License-File: LICENSE
Requires-Dist: openai
Requires-Dist: python-dotenv
